haystack/__init__.py
haystack/environment.py
haystack/errors.py
haystack/lazy_imports.py
haystack/mmh3.py
haystack/schema.py
haystack/silenceable_tqdm.py
haystack/telemetry.py
haystack/agents/__init__.py
haystack/agents/agent_step.py
haystack/agents/base.py
haystack/agents/conversational.py
haystack/agents/types.py
haystack/agents/utils.py
haystack/agents/memory/__init__.py
haystack/agents/memory/base.py
haystack/agents/memory/conversation_memory.py
haystack/agents/memory/conversation_summary_memory.py
haystack/agents/memory/no_memory.py
haystack/cli/README.md
haystack/cli/__init__.py
haystack/cli/entry_point.py
haystack/cli/prompt/__init__.py
haystack/cli/prompt/fetch.py
haystack/document_stores/__init__.py
haystack/document_stores/base.py
haystack/document_stores/deepsetcloud.py
haystack/document_stores/es_converter.py
haystack/document_stores/faiss.py
haystack/document_stores/filter_utils.py
haystack/document_stores/memory.py
haystack/document_stores/mongodb_atlas.py
haystack/document_stores/mongodb_filters.py
haystack/document_stores/opensearch.py
haystack/document_stores/pinecone.py
haystack/document_stores/search_engine.py
haystack/document_stores/sql.py
haystack/document_stores/utils.py
haystack/document_stores/weaviate.py
haystack/document_stores/elasticsearch/__init__.py
haystack/document_stores/elasticsearch/base.py
haystack/document_stores/elasticsearch/es7.py
haystack/document_stores/elasticsearch/es8.py
haystack/modeling/__init__.py
haystack/modeling/infer.py
haystack/modeling/utils.py
haystack/modeling/visual.py
haystack/modeling/data_handler/__init__.py
haystack/modeling/data_handler/data_silo.py
haystack/modeling/data_handler/dataloader.py
haystack/modeling/data_handler/dataset.py
haystack/modeling/data_handler/input_features.py
haystack/modeling/data_handler/inputs.py
haystack/modeling/data_handler/processor.py
haystack/modeling/data_handler/samples.py
haystack/modeling/evaluation/__init__.py
haystack/modeling/evaluation/eval.py
farm_haystack-1.26.4.dist-info/METADATA
farm_haystack-1.26.4.dist-info/WHEEL
farm_haystack-1.26.4.dist-info/entry_points.txt
farm_haystack-1.26.4.dist-info/licenses/LICENSE
farm_haystack-1.26.4.dist-info/RECORD
