Metadata-Version: 2.3
Name: farm-haystack
Version: 1.26.4
Summary: LLM framework to build customizable, production-ready LLM applications. Connect components (models, vector DBs, file converters) to pipelines or agents that can interact with your data.
Project-URL: CI: GitHub, https://github.com/deepset-ai/haystack/actions
Project-URL: Docs: RTD, https://haystack.deepset.ai/overview/intro
Project-URL: GitHub: issues, https://github.com/deepset-ai/haystack/issues
Project-URL: GitHub: repo, https://github.com/deepset-ai/haystack
Project-URL: Homepage, https://github.com/deepset-ai/haystack
Author-email: "deepset.ai" <malte.pietsch@deepset.ai>
Keywords: BERT,QA,Question-Answering,Reader,Retriever,albert,language-model,mrc,roberta,search,semantic-search,squad,transfer-learning,transformer
Classifier: Development Status :: 5 - Production/Stable
Classifier: Intended Audience :: Science/Research
Classifier: License :: Freely Distributable
Classifier: License :: OSI Approved :: Apache Software License
Classifier: Operating System :: OS Independent
Classifier: Programming Language :: Python
Classifier: Programming Language :: Python :: 3
Classifier: Programming Language :: Python :: 3.8
Classifier: Programming Language :: Python :: 3.9
Classifier: Programming Language :: Python :: 3.10
Classifier: Topic :: Scientific/Engineering :: Artificial Intelligence
Requires-Python: >=3.8
Requires-Dist: boilerpy3
Requires-Dist: events
Requires-Dist: httpx
Requires-Dist: jsonschema
Requires-Dist: lazy-imports==0.3.1
Requires-Dist: more-itertools
Requires-Dist: networkx
Requires-Dist: pandas
Requires-Dist: pillow
Requires-Dist: platformdirs
Requires-Dist: posthog
Requires-Dist: prompthub-py==4.0.0
Requires-Dist: pydantic<2
Requires-Dist: quantulum3
Requires-Dist: rank-bm25
Requires-Dist: requests
Requires-Dist: requests-cache<1.0.0
Requires-Dist: scikit-learn>=1.3.0
Requires-Dist: sseclient-py
Requires-Dist: tenacity
Requires-Dist: tiktoken>=0.5.1
Requires-Dist: tqdm
Requires-Dist: transformers<5.0,>=4.46
Provides-Extra: all
Requires-Dist: azure-ai-formrecognizer>=3.2.0b2; extra == 'all'
Requires-Dist: beautifulsoup4; extra == 'all'
Requires-Dist: boto3>=1.28.57; extra == 'all'
Requires-Dist: elastic-transport<8; extra == 'all'
Requires-Dist: elasticsearch<8,>=7.17; extra == 'all'
Requires-Dist: faiss-cpu<=1.7.2,>=1.6.3; extra == 'all'
Requires-Dist: huggingface-hub>=0.5.0; extra == 'all'
Requires-Dist: langdetect; extra == 'all'
Requires-Dist: markdown; extra == 'all'
Requires-Dist: mlflow; extra == 'all'
Requires-Dist: nltk>=3.9.1; extra == 'all'
Requires-Dist: openai-whisper>=20231106; extra == 'all'
Requires-Dist: opensearch-py>=2; extra == 'all'
Requires-Dist: pdf2image>1.14; extra == 'all'
Requires-Dist: pinecone-client<3,>=2.0.11; extra == 'all'
Requires-Dist: psycopg2-binary; (platform_system != 'Windows') and extra == 'all'
Requires-Dist: pymongo>=4.6; extra == 'all'
Requires-Dist: pytesseract>0.3.7; extra == 'all'
Requires-Dist: python-docx; extra == 'all'
Requires-Dist: python-frontmatter; extra == 'all'
Requires-Dist: python-magic-bin; (platform_system == 'Windows') and extra == 'all'
Requires-Dist: python-magic; (platform_system != 'Windows') and extra == 'all'
Requires-Dist: python-pptx<=1.0; extra == 'all'
Requires-Dist: rapidfuzz<2.8.0,>=2.0.15; extra == 'all'
Requires-Dist: scipy>=1.3.2; extra == 'all'
Requires-Dist: selenium>=4.11.0; extra == 'all'
Requires-Dist: sentence-transformers<=3.0.0,>=2.3.1; extra == 'all'
Requires-Dist: seqeval; extra == 'all'
Requires-Dist: sqlalchemy-utils; extra == 'all'
Requires-Dist: sqlalchemy<2,>=1.4.2; extra == 'all'
Requires-Dist: tika; extra == 'all'
Requires-Dist: transformers[sentencepiece,torch]<5.0,>=4.46; extra == 'all'
Requires-Dist: weaviate-client>2; extra == 'all'
Provides-Extra: all-gpu
Requires-Dist: azure-ai-formrecognizer>=3.2.0b2; extra == 'all-gpu'
Requires-Dist: beautifulsoup4; extra == 'all-gpu'
Requires-Dist: boto3>=1.28.57; extra == 'all-gpu'
Requires-Dist: elastic-transport<8; extra == 'all-gpu'
Requires-Dist: elasticsearch<8,>=7.17; extra == 'all-gpu'
Requires-Dist: faiss-gpu<2,>=1.6.3; extra == 'all-gpu'
Requires-Dist: huggingface-hub>=0.5.0; extra == 'all-gpu'
Requires-Dist: langdetect; extra == 'all-gpu'
Requires-Dist: markdown; extra == 'all-gpu'
Requires-Dist: mlflow; extra == 'all-gpu'
Requires-Dist: nltk>=3.9.1; extra == 'all-gpu'
Requires-Dist: openai-whisper>=20231106; extra == 'all-gpu'
Requires-Dist: opensearch-py>=2; extra == 'all-gpu'
Requires-Dist: pdf2image>1.14; extra == 'all-gpu'
Requires-Dist: pinecone-client<3,>=2.0.11; extra == 'all-gpu'
Requires-Dist: psycopg2-binary; (platform_system != 'Windows') and extra == 'all-gpu'
Requires-Dist: pymongo>=4.6; extra == 'all-gpu'
Requires-Dist: pytesseract>0.3.7; extra == 'all-gpu'
Requires-Dist: python-docx; extra == 'all-gpu'
Requires-Dist: python-frontmatter; extra == 'all-gpu'
Requires-Dist: python-magic-bin; (platform_system == 'Windows') and extra == 'all-gpu'
Requires-Dist: python-magic; (platform_system != 'Windows') and extra == 'all-gpu'
Requires-Dist: python-pptx<=1.0; extra == 'all-gpu'
Requires-Dist: rapidfuzz<2.8.0,>=2.0.15; extra == 'all-gpu'
Requires-Dist: scipy>=1.3.2; extra == 'all-gpu'
Requires-Dist: selenium>=4.11.0; extra == 'all-gpu'
Requires-Dist: sentence-transformers<=3.0.0,>=2.3.1; extra == 'all-gpu'
Requires-Dist: seqeval; extra == 'all-gpu'
Requires-Dist: sqlalchemy-utils; extra == 'all-gpu'
Requires-Dist: sqlalchemy<2,>=1.4.2; extra == 'all-gpu'
Requires-Dist: tika; extra == 'all-gpu'
Requires-Dist: transformers[sentencepiece,torch]<5.0,>=4.46; extra == 'all-gpu'
Requires-Dist: weaviate-client>2; extra == 'all-gpu'
Provides-Extra: audio
Requires-Dist: openai-whisper>=20231106; extra == 'audio'
Provides-Extra: aws
Requires-Dist: boto3>=1.28.57; extra == 'aws'
Provides-Extra: colab
Requires-Dist: pillow<=9.0.0; extra == 'colab'
Provides-Extra: crawler
Requires-Dist: selenium>=4.11.0; extra == 'crawler'
Provides-Extra: dev
Requires-Dist: black[jupyter]~=23.0; extra == 'dev'
Requires-Dist: coverage; extra == 'dev'
Requires-Dist: dulwich<1.0.0,>=0.21.0; extra == 'dev'
Requires-Dist: mypy==1.10.0; extra == 'dev'
Requires-Dist: pre-commit; extra == 'dev'
Requires-Dist: psutil; extra == 'dev'
Requires-Dist: pylint; extra == 'dev'
Requires-Dist: pytest; extra == 'dev'
Requires-Dist: pytest-asyncio; extra == 'dev'
Requires-Dist: pytest-cov; extra == 'dev'
Requires-Dist: pytest-custom-exit-code; extra == 'dev'
Requires-Dist: python-multipart; extra == 'dev'
Requires-Dist: reno; extra == 'dev'
Requires-Dist: responses; extra == 'dev'
Requires-Dist: toml; extra == 'dev'
Requires-Dist: tox; extra == 'dev'
Provides-Extra: docstores
Requires-Dist: elastic-transport<8; extra == 'docstores'
Requires-Dist: elasticsearch<8,>=7.17; extra == 'docstores'
Requires-Dist: faiss-cpu<=1.7.2,>=1.6.3; extra == 'docstores'
Requires-Dist: opensearch-py>=2; extra == 'docstores'
Requires-Dist: pinecone-client<3,>=2.0.11; extra == 'docstores'
Requires-Dist: psycopg2-binary; (platform_system != 'Windows') and extra == 'docstores'
Requires-Dist: pymongo>=4.6; extra == 'docstores'
Requires-Dist: sqlalchemy-utils; extra == 'docstores'
Requires-Dist: sqlalchemy<2,>=1.4.2; extra == 'docstores'
Requires-Dist: weaviate-client>2; extra == 'docstores'
Provides-Extra: docstores-gpu
Requires-Dist: elastic-transport<8; extra == 'docstores-gpu'
Requires-Dist: elasticsearch<8,>=7.17; extra == 'docstores-gpu'
Requires-Dist: faiss-gpu<2,>=1.6.3; extra == 'docstores-gpu'
Requires-Dist: opensearch-py>=2; extra == 'docstores-gpu'
Requires-Dist: pinecone-client<3,>=2.0.11; extra == 'docstores-gpu'
Requires-Dist: psycopg2-binary; (platform_system != 'Windows') and extra == 'docstores-gpu'
Requires-Dist: pymongo>=4.6; extra == 'docstores-gpu'
Requires-Dist: sqlalchemy-utils; extra == 'docstores-gpu'
Requires-Dist: sqlalchemy<2,>=1.4.2; extra == 'docstores-gpu'
Requires-Dist: weaviate-client>2; extra == 'docstores-gpu'
Provides-Extra: elasticsearch
Requires-Dist: elastic-transport<8; extra == 'elasticsearch'
Requires-Dist: elasticsearch<8,>=7.17; extra == 'elasticsearch'
Provides-Extra: elasticsearch7
Requires-Dist: elastic-transport<8; extra == 'elasticsearch7'
Requires-Dist: elasticsearch<8,>=7.17; extra == 'elasticsearch7'
Provides-Extra: elasticsearch8
Requires-Dist: elastic-transport<9,>=8; extra == 'elasticsearch8'
Requires-Dist: elasticsearch<9,>=8; extra == 'elasticsearch8'
Provides-Extra: faiss
Requires-Dist: faiss-cpu<=1.7.2,>=1.6.3; extra == 'faiss'
Requires-Dist: psycopg2-binary; (platform_system != 'Windows') and extra == 'faiss'
Requires-Dist: sqlalchemy-utils; extra == 'faiss'
Requires-Dist: sqlalchemy<2,>=1.4.2; extra == 'faiss'
Provides-Extra: faiss-gpu
Requires-Dist: faiss-gpu<2,>=1.6.3; extra == 'faiss-gpu'
Requires-Dist: psycopg2-binary; (platform_system != 'Windows') and extra == 'faiss-gpu'
Requires-Dist: sqlalchemy-utils; extra == 'faiss-gpu'
Requires-Dist: sqlalchemy<2,>=1.4.2; extra == 'faiss-gpu'
Provides-Extra: file-conversion
Requires-Dist: azure-ai-formrecognizer>=3.2.0b2; extra == 'file-conversion'
Requires-Dist: beautifulsoup4; extra == 'file-conversion'
Requires-Dist: markdown; extra == 'file-conversion'
Requires-Dist: python-docx; extra == 'file-conversion'
Requires-Dist: python-frontmatter; extra == 'file-conversion'
Requires-Dist: python-magic-bin; (platform_system == 'Windows') and extra == 'file-conversion'
Requires-Dist: python-magic; (platform_system != 'Windows') and extra == 'file-conversion'
Requires-Dist: python-pptx<=1.0; extra == 'file-conversion'
Requires-Dist: tika; extra == 'file-conversion'
Provides-Extra: formatting
Requires-Dist: black[jupyter]~=23.0; extra == 'formatting'
Provides-Extra: inference
Requires-Dist: huggingface-hub>=0.5.0; extra == 'inference'
Requires-Dist: sentence-transformers<=3.0.0,>=2.3.1; extra == 'inference'
Requires-Dist: transformers[sentencepiece,torch]<5.0,>=4.46; extra == 'inference'
Provides-Extra: metrics
Requires-Dist: mlflow; extra == 'metrics'
Requires-Dist: rapidfuzz<2.8.0,>=2.0.15; extra == 'metrics'
Requires-Dist: scipy>=1.3.2; extra == 'metrics'
Requires-Dist: seqeval; extra == 'metrics'
Provides-Extra: mongodb
Requires-Dist: pymongo>=4.6; extra == 'mongodb'
Provides-Extra: ocr
Requires-Dist: pdf2image>1.14; extra == 'ocr'
Requires-Dist: pytesseract>0.3.7; extra == 'ocr'
Provides-Extra: only-faiss
Requires-Dist: faiss-cpu<=1.7.2,>=1.6.3; extra == 'only-faiss'
Provides-Extra: only-faiss-gpu
Requires-Dist: faiss-gpu<2,>=1.6.3; extra == 'only-faiss-gpu'
Provides-Extra: only-pinecone
Requires-Dist: pinecone-client<3,>=2.0.11; extra == 'only-pinecone'
Provides-Extra: onnx
Requires-Dist: onnxruntime; extra == 'onnx'
Requires-Dist: onnxruntime-tools; extra == 'onnx'
Provides-Extra: onnx-gpu
Requires-Dist: onnxruntime-gpu; extra == 'onnx-gpu'
Requires-Dist: onnxruntime-tools; extra == 'onnx-gpu'
Provides-Extra: opensearch
Requires-Dist: opensearch-py>=2; extra == 'opensearch'
Provides-Extra: pdf
Provides-Extra: pinecone
Requires-Dist: pinecone-client<3,>=2.0.11; extra == 'pinecone'
Requires-Dist: psycopg2-binary; (platform_system != 'Windows') and extra == 'pinecone'
Requires-Dist: sqlalchemy-utils; extra == 'pinecone'
Requires-Dist: sqlalchemy<2,>=1.4.2; extra == 'pinecone'
Provides-Extra: preprocessing
Requires-Dist: langdetect; extra == 'preprocessing'
Requires-Dist: nltk>=3.9.1; extra == 'preprocessing'
Provides-Extra: ray
Requires-Dist: aiorwlock<2,>=1.3.0; extra == 'ray'
Requires-Dist: ray[serve]!=1.12.0,<2,>=1.9.1; (platform_system == 'Windows') and extra == 'ray'
Requires-Dist: ray[serve]<2,>=1.9.1; (platform_system != 'Windows') and extra == 'ray'
Provides-Extra: sql
Requires-Dist: psycopg2-binary; (platform_system != 'Windows') and extra == 'sql'
Requires-Dist: sqlalchemy-utils; extra == 'sql'
Requires-Dist: sqlalchemy<2,>=1.4.2; extra == 'sql'
Provides-Extra: weaviate
Requires-Dist: weaviate-client>2; extra == 'weaviate'
